sdk/__init__.py
sdk/flickpay.py
sdk/py.typed
sdk/types.py
flick_payment-0.0.2.dist-info/LICENCE.txt
flick_payment-0.0.2.dist-info/METADATA
flick_payment-0.0.2.dist-info/WHEEL
flick_payment-0.0.2.dist-info/top_level.txt
flick_payment-0.0.2.dist-info/RECORD
