Metadata-Version: 2.1
Name: flick_payment
Version: 0.0.2
Summary: Flick Python SDKs contains FlickPay inflow and outflow solutions
Home-page: https://merchant.getflick.co/
Author: Quraba inc
Author-email: kingsley@getflick.app
License: MIT
Keywords: flickpaysdk,card,bank,transfer,payout,inflow,outflow
License-File: LICENCE.txt
